<!--************************  CustomOreGen Minecraft Ores Module *********************************
*
*   This file contains Presets, Options, and Distributions for the Matallurgy Mod Ore:
*   Prometheum, Deep Iron, Infuscolium, Oureclase, Astral Silver, Carmot, Mithril, Rubracium, Orichalcum, Adamantine, Atlarus.
*
***********************************************************************************************-->
<ConfigSection>

    <!--***************************   Options + Symbols   ***********************************
    *
    *   Below are options and symbols for Metallurgy Fantasy Ores. Each ore has a "type" option 
    *   corresponding to select which distribution is used for that ore in the
    *   overworld, and 3 mystcraft symbols for selecting distributions in mystcraft ages.
    *
    *   The ore also has its own overall "frequency" and "size" multipliers.  These are 
    *   provided so people can tweak the rarity of each ore from the options file rather 
    *   than having to edit the config directly.
    *
    *************************************************************************************-->
    <ConfigSection>
    
        <OptionDisplayGroup name='groupMetallurgyFantasyOres' displayName='Metallurgy Fantasy Ores' displayState='shown'>
            <Description> 
                Distribution options for the Metallurgy Fantasy Ores  (Prometheum, Deep Iron, Infuscolium, Oureclase, Astral Silver, Carmot, Mithril, Rubracium, Orichalcum, Adamantine, Atlarus).
            </Description>
        </OptionDisplayGroup>


        <!--*******************   Prometheum   ***********************-->
        <ConfigSection>
        
            <OptionChoice name='prometheumDist' default='vanillaStdGen' displayState='shown' displayGroup='groupMetallurgyFantasyOres'>
                <Description> Controls how Prometheum is generated. </Description>
                <DisplayName>Prometheum Type</DisplayName>

                <Choice value='vanillaStdGen' displayValue='Clusters'>
                    <Description> 
                        Small evenly scattered clusters of ore.  This is the vanilla Minecraft style of generation/distribution.
                    </Description>
                </Choice>

                <Choice value='none' displayValue='None' description='No prometheum is generated at all.'/>

            </OptionChoice>

            
            <OptionNumeric name='prometheumFreq' default='1'  min='0' max='5' displayState='hidden' displayGroup='groupMetallurgyFantasyOres'>
                <Description> Frequency multiplier for Prometheum distributions. </Description>
                <DisplayName>Prometheum Freq.</DisplayName>
            </OptionNumeric> 
            
            <OptionNumeric name='prometheumSize' default='1'  min='0' max='5' displayState='hidden' displayGroup='groupMetallurgyFantasyOres'>
                <Description> Size multiplier for Prometheum distributions. </Description>
                <DisplayName>Prometheum Size</DisplayName>
            </OptionNumeric>

            <MystcraftSymbol name='prometheumClusters' displayName='Prometheum Clusters'/>
       
        </ConfigSection>        
        <!-- ********** / Prometheum  ********** -->


        <!--*******************   DeepIron   ***********************-->
        <ConfigSection>
        
            <OptionChoice name='deepironDist' default='vanillaStdGen' displayState='shown' displayGroup='groupMetallurgyFantasyOres'>
                <Description> Controls how Deep Iron is generated. </Description>
                <DisplayName>DeepIron Type</DisplayName>

                <Choice value='vanillaStdGen' displayValue='Clusters'>
                    <Description> 
                        Small evenly scattered clusters of ore.  This is the vanilla Minecraft style of generation/distribution.
                    </Description>
                </Choice>

                <Choice value='none' displayValue='None' description='No deepiron is generated at all.'/>

            </OptionChoice>

            
            <OptionNumeric name='deepironFreq' default='1'  min='0' max='5' displayState='hidden' displayGroup='groupMetallurgyFantasyOres'>
                <Description> Frequency multiplier for Deep Iron distributions. </Description>
                <DisplayName>DeepIron Freq.</DisplayName>
            </OptionNumeric> 
            
            <OptionNumeric name='deepironSize' default='1'  min='0' max='5' displayState='hidden' displayGroup='groupMetallurgyFantasyOres'>
                <Description> Size multiplier for Deep Iron distributions. </Description>
                <DisplayName>DeepIron Size</DisplayName>
            </OptionNumeric>

            <MystcraftSymbol name='deepironClusters' displayName='DeepIron Clusters'/>
       
        </ConfigSection>        
        <!-- ********** / DeepIron  ********** -->


        <!--*******************   Infuscolium   ***********************-->
        <ConfigSection>
        
            <OptionChoice name='infuscoliumDist' default='vanillaStdGen' displayState='shown' displayGroup='groupMetallurgyFantasyOres'>
                <Description> Controls how Infuscolium is generated. </Description>
                <DisplayName>Infuscolium Type</DisplayName>

                <Choice value='vanillaStdGen' displayValue='Clusters'>
                    <Description> 
                        Small evenly scattered clusters of ore.  This is the vanilla Minecraft style of generation/distribution.
                    </Description>
                </Choice>

                <Choice value='none' displayValue='None' description='No infuscolium is generated at all.'/>

            </OptionChoice>

            
            <OptionNumeric name='infuscoliumFreq' default='1'  min='0' max='5' displayState='hidden' displayGroup='groupMetallurgyFantasyOres'>
                <Description> Frequency multiplier for Infuscolium distributions. </Description>
                <DisplayName>Infuscolium Freq.</DisplayName>
            </OptionNumeric> 
            
            <OptionNumeric name='infuscoliumSize' default='1'  min='0' max='5' displayState='hidden' displayGroup='groupMetallurgyFantasyOres'>
                <Description> Size multiplier for Infuscolium distributions. </Description>
                <DisplayName>Infuscolium Size</DisplayName>
            </OptionNumeric>

            <MystcraftSymbol name='infuscoliumClusters' displayName='Infuscolium Clusters'/>
       
        </ConfigSection>        
        <!-- ********** / Infuscolium  ********** -->


        <!--*******************   Oureclase   ***********************-->
        <ConfigSection>
        
            <OptionChoice name='oureclaseDist' default='vanillaStdGen' displayState='shown' displayGroup='groupMetallurgyFantasyOres'>
                <Description> Controls how Oureclase is generated. </Description>
                <DisplayName>Oureclase Type</DisplayName>

                <Choice value='vanillaStdGen' displayValue='Clusters'>
                    <Description> 
                        Small evenly scattered clusters of ore.  Found between layers 12 and 48. This is the vanilla Minecraft style of generation/distribution.
                    </Description>
                </Choice>

                <Choice value='none' displayValue='None' description='No oureclase is generated at all.'/>

            </OptionChoice>

            
            <OptionNumeric name='oureclaseFreq' default='1'  min='0' max='5' displayState='hidden' displayGroup='groupMetallurgyFantasyOres'>
                <Description> Frequency multiplier for Oureclase distributions. </Description>
                <DisplayName>Oureclase Freq.</DisplayName>
            </OptionNumeric> 
            
            <OptionNumeric name='oureclaseSize' default='1'  min='0' max='5' displayState='hidden' displayGroup='groupMetallurgyFantasyOres'>
                <Description> Size multiplier for Oureclase distributions. </Description>
                <DisplayName>Oureclase Size</DisplayName>
            </OptionNumeric>

            <MystcraftSymbol name='oureclaseClusters' displayName='Oureclase Clusters'/>
       
        </ConfigSection>        
        <!-- ********** / Oureclase  ********** -->


        <!--*******************   Astral Silver   ***********************-->
        <ConfigSection>
        
            <OptionChoice name='astralsilverDist' default='vanillaStdGen' displayState='shown' displayGroup='groupMetallurgyFantasyOres'>
                <Description> Controls how AstralSilver is generated. </Description>
                <DisplayName>AstralSilver Type</DisplayName>

                <Choice value='vanillaStdGen' displayValue='Clusters'>
                    <Description> 
                        Small evenly scattered clusters of ore.  This is the vanilla Minecraft style of generation/distribution.
                    </Description>
                </Choice>

                <Choice value='none' displayValue='None' description='No astralsilver is generated at all.'/>

            </OptionChoice>

            
            <OptionNumeric name='astralsilverFreq' default='1'  min='0' max='5' displayState='hidden' displayGroup='groupMetallurgyFantasyOres'>
                <Description> Frequency multiplier for AstralSilver distributions. </Description>
                <DisplayName>AstralSilver Freq.</DisplayName>
            </OptionNumeric> 
            
            <OptionNumeric name='astralsilverSize' default='1'  min='0' max='5' displayState='hidden' displayGroup='groupMetallurgyFantasyOres'>
                <Description> Size multiplier for AstralSilver distributions. </Description>
                <DisplayName>AstralSilver Size</DisplayName>
            </OptionNumeric>

            <MystcraftSymbol name='astralsilverClusters' displayName='AstralSilver Clusters'/>
       
        </ConfigSection>        
        <!-- ********** / AstralSilver  ********** -->


        <!--*******************   Carmot   ***********************-->
        <ConfigSection>
        
            <OptionChoice name='carmotDist' default='vanillaStdGen' displayState='shown' displayGroup='groupMetallurgyFantasyOres'>
                <Description> Controls how Carmot is generated. </Description>
                <DisplayName>Carmot Type</DisplayName>

                <Choice value='vanillaStdGen' displayValue='Clusters'>
                    <Description> 
                        Small evenly scattered clusters of ore.  This is the vanilla Minecraft style of generation/distribution.
                    </Description>
                </Choice>

                <Choice value='none' displayValue='None' description='No carmot is generated at all.'/>

            </OptionChoice>

            
            <OptionNumeric name='carmotFreq' default='1'  min='0' max='5' displayState='hidden' displayGroup='groupMetallurgyFantasyOres'>
                <Description> Frequency multiplier for Carmot distributions. </Description>
                <DisplayName>Carmot Freq.</DisplayName>
            </OptionNumeric> 
            
            <OptionNumeric name='carmotSize' default='1'  min='0' max='5' displayState='hidden' displayGroup='groupMetallurgyFantasyOres'>
                <Description> Size multiplier for Carmot distributions. </Description>
                <DisplayName>Carmot Size</DisplayName>
            </OptionNumeric>

            <MystcraftSymbol name='carmotClusters' displayName='Carmot Clusters'/>
       
        </ConfigSection>        
        <!-- ********** / Carmot  ********** -->


        <!--*******************   Mithril   ***********************-->
        <ConfigSection>
        
            <OptionChoice name='mithrilDist' default='vanillaStdGen' displayState='shown' displayGroup='groupMetallurgyFantasyOres'>
                <Description> Controls how Mithril is generated. </Description>
                <DisplayName>Mithril Type</DisplayName>

                <Choice value='vanillaStdGen' displayValue='Clusters'>
                    <Description> 
                        Small evenly scattered clusters of ore.  Found between layers 18 and 42. This is the vanilla Minecraft style of generation/distribution.
                    </Description>
                </Choice>

                <Choice value='none' displayValue='None' description='No mithril is generated at all.'/>

            </OptionChoice>

            
            <OptionNumeric name='mithrilFreq' default='1'  min='0' max='5' displayState='hidden' displayGroup='groupMetallurgyFantasyOres'>
                <Description> Frequency multiplier for Mithril distributions. </Description>
                <DisplayName>Mithril Freq.</DisplayName>
            </OptionNumeric> 
            
            <OptionNumeric name='mithrilSize' default='1'  min='0' max='5' displayState='hidden' displayGroup='groupMetallurgyFantasyOres'>
                <Description> Size multiplier for Mithril distributions. </Description>
                <DisplayName>Mithril Size</DisplayName>
            </OptionNumeric>

            <MystcraftSymbol name='mithrilClusters' displayName='Mithril Clusters'/>
       
        </ConfigSection>        
        <!-- ********** / Mithril  ********** -->


        <!--*******************   Rubracium   ***********************-->
        <ConfigSection>
        
            <OptionChoice name='rubraciumDist' default='vanillaStdGen' displayState='shown' displayGroup='groupMetallurgyFantasyOres'>
                <Description> Controls how Rubracium is generated. </Description>
                <DisplayName>Rubracium Type</DisplayName>

                <Choice value='vanillaStdGen' displayValue='Clusters'>
                    <Description> 
                        Small evenly scattered clusters of ore.  Found below layer 32. This is the vanilla Minecraft style of generation/distribution.
                    </Description>
                </Choice>

                <Choice value='none' displayValue='None' description='No rubracium is generated at all.'/>

            </OptionChoice>

            
            <OptionNumeric name='rubraciumFreq' default='1'  min='0' max='5' displayState='hidden' displayGroup='groupMetallurgyFantasyOres'>
                <Description> Frequency multiplier for Rubracium distributions. </Description>
                <DisplayName>Rubracium Freq.</DisplayName>
            </OptionNumeric> 
            
            <OptionNumeric name='rubraciumSize' default='1'  min='0' max='5' displayState='hidden' displayGroup='groupMetallurgyFantasyOres'>
                <Description> Size multiplier for Rubracium distributions. </Description>
                <DisplayName>Rubracium Size</DisplayName>
            </OptionNumeric>

            <MystcraftSymbol name='rubraciumClusters' displayName='Rubracium Clusters'/>
       
        </ConfigSection>        
        <!-- ********** / Rubracium  ********** -->


        <!--*******************   Orichalcum   ***********************-->
        <ConfigSection>
        
            <OptionChoice name='orichalcumDist' default='vanillaStdGen' displayState='shown' displayGroup='groupMetallurgyFantasyOres'>
                <Description> Controls how Orichalcum is generated. </Description>
                <DisplayName>Orichalcum Type</DisplayName>

                <Choice value='vanillaStdGen' displayValue='Clusters'>
                    <Description> 
                        Small evenly scattered clusters of ore.  Found between layers 6 and 20. This is the vanilla Minecraft style of generation/distribution.
                    </Description>
                </Choice>

                <Choice value='none' displayValue='None' description='No orichalcum is generated at all.'/>

            </OptionChoice>

            
            <OptionNumeric name='orichalcumFreq' default='1'  min='0' max='5' displayState='hidden' displayGroup='groupMetallurgyFantasyOres'>
                <Description> Frequency multiplier for Orichalcum distributions. </Description>
                <DisplayName>Orichalcum Freq.</DisplayName>
            </OptionNumeric> 
            
            <OptionNumeric name='orichalcumSize' default='1'  min='0' max='5' displayState='hidden' displayGroup='groupMetallurgyFantasyOres'>
                <Description> Size multiplier for Orichalcum distributions. </Description>
                <DisplayName>Orichalcum Size</DisplayName>
            </OptionNumeric>

            <MystcraftSymbol name='orichalcumClusters' displayName='Orichalcum Clusters'/>
       
        </ConfigSection>        
        <!-- ********** / Orichalcum  ********** -->


        <!--*******************   Adamantine   ***********************-->
        <ConfigSection>
        
            <OptionChoice name='adamantineDist' default='vanillaStdGen' displayState='shown' displayGroup='groupMetallurgyFantasyOres'>
                <Description> Controls how Adamantine is generated. </Description>
                <DisplayName>Adamantine Type</DisplayName>

                <Choice value='vanillaStdGen' displayValue='Clusters'>
                    <Description> 
                        Small evenly scattered clusters of ore. Found below layer 10. This is the vanilla Minecraft style of generation/distribution.
                    </Description>
                </Choice>

                <Choice value='none' displayValue='None' description='No adamantine is generated at all.'/>

            </OptionChoice>

            
            <OptionNumeric name='adamantineFreq' default='1'  min='0' max='5' displayState='hidden' displayGroup='groupMetallurgyFantasyOres'>
                <Description> Frequency multiplier for Adamantine distributions. </Description>
                <DisplayName>Adamantine Freq.</DisplayName>
            </OptionNumeric> 
            
            <OptionNumeric name='adamantineSize' default='1'  min='0' max='5' displayState='hidden' displayGroup='groupMetallurgyFantasyOres'>
                <Description> Size multiplier for Adamantine distributions. </Description>
                <DisplayName>Adamantine Size</DisplayName>
            </OptionNumeric>

            <MystcraftSymbol name='adamantineClusters' displayName='Adamantine Clusters'/>
       
        </ConfigSection>        
        <!-- ********** / Adamantine  ********** -->


        <!--*******************   Atlarus   ***********************-->
        <ConfigSection>
        
            <OptionChoice name='atlarusDist' default='vanillaStdGen' displayState='shown' displayGroup='groupMetallurgyFantasyOres'>
                <Description> Controls how Atlarus is generated. </Description>
                <DisplayName>Atlarus Type</DisplayName>

                <Choice value='vanillaStdGen' displayValue='Clusters'>
                    <Description> 
                        Small evenly scattered clusters of ore. Found below layer 10. This is the vanilla Minecraft style of generation/distribution.
                    </Description>
                </Choice>

                <Choice value='none' displayValue='None' description='No atlarus is generated at all.'/>

            </OptionChoice>

            
            <OptionNumeric name='atlarusFreq' default='1'  min='0' max='5' displayState='hidden' displayGroup='groupMetallurgyFantasyOres'>
                <Description> Frequency multiplier for Atlarus distributions. </Description>
                <DisplayName>Atlarus Freq.</DisplayName>
            </OptionNumeric> 
            
            <OptionNumeric name='atlarusSize' default='1'  min='0' max='5' displayState='hidden' displayGroup='groupMetallurgyFantasyOres'>
                <Description> Size multiplier for Atlarus distributions. </Description>
                <DisplayName>Atlarus Size</DisplayName>
            </OptionNumeric>

            <MystcraftSymbol name='atlarusClusters' displayName='Atlarus Clusters'/>
       
        </ConfigSection>        
        <!-- ********** / Atlarus  ********** -->




        <!-- Menu Options for Additional Ores can go here... -->

        <!--*******************   (Ore)   ***********************-->


        <!-- ********** / (Ore)  ********** -->



     </ConfigSection>   


    <!--*****************************   Distributions   *************************************
    *   
    *   Currently this Metallurgy Mod Config ONLY uses the Cluster (Stanard) Distribution.
    *
    *     Vanilla Clusters:
    *       A re-creation of the vanilla ore generation using the StandardGen algorithm.
    *
    *************************************************************************************-->
    <IfCondition condition=':= (dimension.generator = "RandomLevelSource") &amp;
                            (dimension.id = 0)'>
        
        <!--**********   Vanilla Deposit Removal   *************-->
        <Substitute name='StandardOreSubstitute' block='stone'>
            <Description> 
                Replace vanilla-generated ore clusters with stone.   
            </Description>
            <Comment>  
                The global option deferredPopulationRange must be large enough to catch all ore clusters (>= 32).
            </Comment>

            <Replaces block='906:0'/>	<!--  Prometheum  -->
            <Replaces block='906:1'/>	<!--  Deep Iron  -->
            <Replaces block='906:2'/>	<!--  Infuscolium  -->
            <Replaces block='906:4'/>	<!--  Oureclase  -->
            <Replaces block='906:5'/>	<!--  Astral Silver  -->
            <Replaces block='906:6'/>	<!--  Carmot  -->
            <Replaces block='906:7'/>	<!--  Mithril  -->
            <Replaces block='906:8'/>	<!--  Rubracium  -->
            <Replaces block='906:11'/>	<!--  Orichalcum  -->
            <Replaces block='906:13'/>	<!--  Adamantine  -->
            <Replaces block='906:14'/>	<!--  Atlarus  -->


        </Substitute>
        
        <!--*******************   Prometheum   ***********************-->
        <ConfigSection>
        
	  <!-- *****  Standard Cluster  ***** -->
            <IfCondition condition=':= if(age, age.prometheumClusters > 0, prometheumDist = "vanillaStdGen")'>    

                <StandardGen name='PrometheumStandard' block='906:0' inherits='PresetStandardGen'> 
                    <Description> Equivalent to vanilla minecraft Cluster distribution. </Description>
                    <DrawWireframe>:=drawWireframes</DrawWireframe>
                    <WireframeColor>0x60101010</WireframeColor>

                    <Setting name='Size' avg=':= 0.75 * prometheumSize * _default_'/> 
                    <Setting name='Frequency' avg=':= 0.25 * prometheumFreq * if(age,age.prometheumClusters,1) * _default_'/>
                    <Setting name='Height' avg=':= 128/128 * dimension.groundLevel' range=':= 128/128 * dimension.groundLevel'/>

  		  <!--1 = 100%  (Normal loads full amount).  0.5 = 50%  (Loads Half as much).  0 = 0%  (None loads in this Biome). -->
                    <BiomeType name='.*' weight='1'/>
                    <Biome name='Hell.*' weight='-1'/>

                </StandardGen>


		<!-- More Distribution Types can go here -->


            </IfCondition>   
            
        </ConfigSection>
        <!-- ********** / Prometheum ********** -->


        <!--*******************   DeepIron   ***********************-->
        <ConfigSection>
        
	  <!-- *****  Standard Cluster  ***** -->
            <IfCondition condition=':= if(age, age.deepironClusters > 0, deepironDist = "vanillaStdGen")'>    

                <StandardGen name='DeepIronStandard' block='906:1' inherits='PresetStandardGen'> 
                    <Description> Equivalent to vanilla minecraft Cluster distribution. </Description>
                    <DrawWireframe>:=drawWireframes</DrawWireframe>
                    <WireframeColor>0x60101010</WireframeColor>

                    <Setting name='Size' avg=':= 0.5 * deepironSize * _default_'/> 
                    <Setting name='Frequency' avg=':= 0.25 * deepironFreq * if(age,age.deepironClusters,1) * _default_'/>
                    <Setting name='Height' avg=':= 128/128 * dimension.groundLevel' range=':= 128/128 * dimension.groundLevel'/>

  		  <!--1 = 100%  (Normal loads full amount).  0.5 = 50%  (Loads Half as much).  0 = 0%  (None loads in this Biome). -->
                    <BiomeType name='.*' weight='1'/>
                    <Biome name='Hell.*' weight='-1'/>

                </StandardGen>


		<!-- More Distribution Types can go here -->


            </IfCondition>   
            
        </ConfigSection>
        <!-- ********** / DeepIron ********** -->


        <!--*******************   Infuscolium   ***********************-->
        <ConfigSection>
        
	  <!-- *****  Standard Cluster  ***** -->
            <IfCondition condition=':= if(age, age.infuscoliumClusters > 0, infuscoliumDist = "vanillaStdGen")'>    

                <StandardGen name='InfuscoliumStandard' block='906:2' inherits='PresetStandardGen'> 
                    <Description> Equivalent to vanilla minecraft Cluster distribution. </Description>
                    <DrawWireframe>:=drawWireframes</DrawWireframe>
                    <WireframeColor>0x60101010</WireframeColor>

                    <Setting name='Size' avg=':= 0.5 * infuscoliumSize * _default_'/> 
                    <Setting name='Frequency' avg=':= 0.25 * infuscoliumFreq * if(age,age.infuscoliumClusters,1) * _default_'/>
                    <Setting name='Height' avg=':= 128/128 * dimension.groundLevel' range=':= 128/128 * dimension.groundLevel'/>

  		  <!--1 = 100%  (Normal loads full amount).  0.5 = 50%  (Loads Half as much).  0 = 0%  (None loads in this Biome). -->
                    <BiomeType name='.*' weight='1'/>
                    <Biome name='Hell.*' weight='-1'/>

                </StandardGen>


		<!-- More Distribution Types can go here -->


            </IfCondition>   
            
        </ConfigSection>
        <!-- ********** / Infuscolium ********** -->


        <!--*******************   Oureclase   ***********************-->
        <ConfigSection>
        
	  <!-- *****  Standard Cluster  ***** -->
            <IfCondition condition=':= if(age, age.oureclaseClusters > 0, oureclaseDist = "vanillaStdGen")'>    

                <StandardGen name='OureclaseStandard' block='906:4' inherits='PresetStandardGen'> 
                    <Description> Equivalent to vanilla minecraft Cluster distribution. </Description>
                    <DrawWireframe>:=drawWireframes</DrawWireframe>
                    <WireframeColor>0x60101010</WireframeColor>

                    <Setting name='Size' avg=':= 0.375 * oureclaseSize * _default_'/> 
                    <Setting name='Frequency' avg=':= 0.2 * oureclaseFreq * if(age,age.oureclaseClusters,1) * _default_'/>
                    <Setting name='Height' avg=':= 64/128 * dimension.groundLevel' range=':= 32/128 * dimension.groundLevel'/>

  		  <!--1 = 100%  (Normal loads full amount).  0.5 = 50%  (Loads Half as much).  0 = 0%  (None loads in this Biome). -->
                    <BiomeType name='.*' weight='0.5'/>
                    <BiomeType name='Plains.*' weight='-0.2'/>
                    <Biome name='Extreme.*' weight='0.5'/>
                    <Biome name='Hills.*' weight='0.5'/>
                    <Biome name='Cold.*' weight='0.5'/>
                    <Biome name='Hell.*' weight='-1'/>

                </StandardGen>


		<!-- More Distribution Types can go here -->


            </IfCondition>   
            
        </ConfigSection>
        <!-- ********** / Oureclase ********** -->


        <!--*******************   AstralSilver   ***********************-->
        <ConfigSection>
        
	  <!-- *****  Standard Cluster  ***** -->
            <IfCondition condition=':= if(age, age.astralsilverClusters > 0, astralsilverDist = "vanillaStdGen")'>    

                <StandardGen name='AstralSilverStandard' block='906:5' inherits='PresetStandardGen'> 
                    <Description> Equivalent to vanilla minecraft Cluster distribution. </Description>
                    <DrawWireframe>:=drawWireframes</DrawWireframe>
                    <WireframeColor>0x60101010</WireframeColor>

                    <Setting name='Size' avg=':= 0.375 * astralsilverSize * _default_'/> 
                    <Setting name='Frequency' avg=':= 0.2 * astralsilverFreq * if(age,age.astralsilverClusters,1) * _default_'/>
                    <Setting name='Height' avg=':= 128/128 * dimension.groundLevel' range=':= 128/128 * dimension.groundLevel'/>

  		  <!--1 = 100%  (Normal loads full amount).  0.5 = 50%  (Loads Half as much).  0 = 0%  (None loads in this Biome). -->
                    <BiomeType name='.*' weight='1'/>
                    <BiomeType name='Plains.*' weight='-0.5'/>
                    <Biome name='Hell.*' weight='-1'/>

                </StandardGen>


		<!-- More Distribution Types can go here -->


            </IfCondition>   
            
        </ConfigSection>
        <!-- ********** / AstralSilver ********** -->


        <!--*******************   Carmot   ***********************-->
        <ConfigSection>
        
	  <!-- *****  Standard Cluster  ***** -->
            <IfCondition condition=':= if(age, age.carmotClusters > 0, carmotDist = "vanillaStdGen")'>    

                <StandardGen name='CarmotStandard' block='906:6' inherits='PresetStandardGen'> 
                    <Description> Equivalent to vanilla minecraft Cluster distribution. </Description>
                    <DrawWireframe>:=drawWireframes</DrawWireframe>
                    <WireframeColor>0x60101010</WireframeColor>

                    <Setting name='Size' avg=':= 0.375 * carmotSize * _default_'/> 
                    <Setting name='Frequency' avg=':= 0.15 * carmotFreq * if(age,age.carmotClusters,1) * _default_'/>
                    <Setting name='Height' avg=':= 128/128 * dimension.groundLevel' range=':= 128/128 * dimension.groundLevel'/>

  		  <!--1 = 100%  (Normal loads full amount).  0.5 = 50%  (Loads Half as much).  0 = 0%  (None loads in this Biome). -->
                    <BiomeType name='.*' weight='1'/>
                    <Biome name='Hell.*' weight='-1'/>

                </StandardGen>


		<!-- More Distribution Types can go here -->


            </IfCondition>   
            
        </ConfigSection>
        <!-- ********** / Carmot ********** -->


        <!--*******************   Mithril   ***********************-->
        <ConfigSection>
        
	  <!-- *****  Standard Cluster  ***** -->
            <IfCondition condition=':= if(age, age.mithrilClusters > 0, mithrilDist = "vanillaStdGen")'>    

                <StandardGen name='MithrilStandard' block='906:7' inherits='PresetStandardGen'> 
                    <Description> Equivalent to vanilla minecraft Cluster distribution. </Description>
                    <DrawWireframe>:=drawWireframes</DrawWireframe>
                    <WireframeColor>0x60101010</WireframeColor>

                    <Setting name='Size' avg=':= 0.375 * mithrilSize * _default_'/> 
                    <Setting name='Frequency' avg=':= 0.15 * mithrilFreq * if(age,age.mithrilClusters,1) * _default_'/>
                    <Setting name='Height' avg=':= 64/128 * dimension.groundLevel' range=':= 20/128 * dimension.groundLevel'/>

  		  <!--1 = 100%  (Normal loads full amount).  0.5 = 50%  (Loads Half as much).  0 = 0%  (None loads in this Biome). -->
                    <BiomeType name='.*' weight='0.60'/>
                    <Biome name='Extreme.*' weight='0.5'/>
                    <Biome name='Hills.*' weight='0.5'/>
                    <Biome name='Cold.*' weight='0.5'/>
                    <Biome name='Ice.*' weight='0.5'/>
                    <Biome name='Frozen.*' weight='0.2'/>
                    <Biome name='Jungle.*' weight='0.2'/>
                    <Biome name='Forest.*' weight='0.2'/>
                    <Biome name='Hell.*' weight='-1'/>

                </StandardGen>


		<!-- More Distribution Types can go here -->


            </IfCondition>   
            
        </ConfigSection>
        <!-- ********** / Mithril ********** -->


        <!--*******************   Rubracium   ***********************-->
        <ConfigSection>
        
	  <!-- *****  Standard Cluster  ***** -->
            <IfCondition condition=':= if(age, age.rubraciumClusters > 0, rubraciumDist = "vanillaStdGen")'>    

                <StandardGen name='RubraciumStandard' block='906:8' inherits='PresetStandardGen'> 
                    <Description> Equivalent to vanilla minecraft Cluster distribution. </Description>
                    <DrawWireframe>:=drawWireframes</DrawWireframe>
                    <WireframeColor>0x60101010</WireframeColor>

                    <Setting name='Size' avg=':= 0.375 * rubraciumSize * _default_'/> 
                    <Setting name='Frequency' avg=':= 0.1 * rubraciumFreq * if(age,age.rubraciumClusters,1) * _default_'/>
                    <Setting name='Height' avg=':= 32/128 * dimension.groundLevel' range=':= 32/128 * dimension.groundLevel'/>

  		  <!--1 = 100%  (Normal loads full amount).  0.5 = 50%  (Loads Half as much).  0 = 0%  (None loads in this Biome). -->
                    <BiomeType name='.*' weight='0.5'/>
                    <Biome name='Extreme.*' weight='0.5'/>
                    <Biome name='Hills.*' weight='0.5'/>
                    <Biome name='Cold.*' weight='0.5'/>
                    <Biome name='Ice.*' weight='0.5'/>
                    <Biome name='Frozen.*' weight='0.25'/>
                    <Biome name='Jungle.*' weight='0.25'/>
                    <Biome name='Forest.*' weight='0.25'/>
                    <Biome name='Desert.*' weight='0.25'/>
                    <Biome name='Hell.*' weight='-1'/>

                </StandardGen>


		<!-- More Distribution Types can go here -->


            </IfCondition>   
            
        </ConfigSection>
        <!-- ********** / Rubracium ********** -->


        <!--*******************   Orichalcum   ***********************-->
        <ConfigSection>
        
	  <!-- *****  Standard Cluster  ***** -->
            <IfCondition condition=':= if(age, age.orichalcumClusters > 0, orichalcumDist = "vanillaStdGen")'>    

                <StandardGen name='OrichalcumStandard' block='906:11' inherits='PresetStandardGen'> 
                    <Description> Equivalent to vanilla minecraft Cluster distribution. </Description>
                    <DrawWireframe>:=drawWireframes</DrawWireframe>
                    <WireframeColor>0x60101010</WireframeColor>

                    <Setting name='Size' avg=':= 0.5 * orichalcumSize * _default_'/> 
                    <Setting name='Frequency' avg=':= 0.1 * orichalcumFreq * if(age,age.orichalcumClusters,1) * _default_'/>
                    <Setting name='Height' avg=':= 30/128 * dimension.groundLevel' range=':= 10/128 * dimension.groundLevel'/>

  		  <!--1 = 100%  (Normal loads full amount).  0.5 = 50%  (Loads Half as much).  0 = 0%  (None loads in this Biome). -->
                    <BiomeType name='.*' weight='0.5'/>
                    <Biome name='Extreme.*' weight='0.5'/>
                    <Biome name='Hills.*' weight='0.5'/>
                    <Biome name='Cold.*' weight='0.5'/>
                    <Biome name='Ice.*' weight='0.5'/>
                    <Biome name='Frozen.*' weight='0.25'/>
                    <Biome name='Jungle.*' weight='0.25'/>
                    <Biome name='Forest.*' weight='0.25'/>
                    <Biome name='Hell.*' weight='-1'/>

                </StandardGen>


		<!-- More Distribution Types can go here -->


            </IfCondition>   
            
        </ConfigSection>
        <!-- ********** / Orichalcum ********** -->


        <!--*******************   Adamantine   ***********************-->
        <ConfigSection>
        
	  <!-- *****  Standard Cluster  ***** -->
            <IfCondition condition=':= if(age, age.adamantineClusters > 0, adamantineDist = "vanillaStdGen")'>    

                <StandardGen name='AdamantineStandard' block='906:13' inherits='PresetStandardGen'> 
                    <Description> Equivalent to vanilla minecraft Cluster distribution. </Description>
                    <DrawWireframe>:=drawWireframes</DrawWireframe>
                    <WireframeColor>0x60101010</WireframeColor>

                    <Setting name='Size' avg=':= 0.375 * adamantineSize * _default_'/> 
                    <Setting name='Frequency' avg=':= 0.05 * adamantineFreq * if(age,age.adamantineClusters,1) * _default_'/>
                    <Setting name='Height' avg=':= 10/128 * dimension.groundLevel' range=':= 10/128 * dimension.groundLevel'/>

  		  <!--1 = 100%  (Normal loads full amount).  0.5 = 50%  (Loads Half as much).  0 = 0%  (None loads in this Biome). -->
                    <BiomeType name='.*' weight='0.5'/>
                    <Biome name='Extreme.*' weight='0.5'/>
                    <Biome name='Hills.*' weight='0.5'/>
                    <Biome name='Cold.*' weight='0.5'/>
                    <Biome name='Ice.*' weight='0.5'/>
                    <Biome name='Frozen.*' weight='0.25'/>
                    <Biome name='Hell.*' weight='-1'/>

                </StandardGen>


		<!-- More Distribution Types can go here -->


            </IfCondition>   
            
        </ConfigSection>
        <!-- ********** / Adamantine ********** -->


        <!--*******************   Atlarus   ***********************-->
        <ConfigSection>
        
	  <!-- *****  Standard Cluster  ***** -->
            <IfCondition condition=':= if(age, age.atlarusClusters > 0, atlarusDist = "vanillaStdGen")'>    

                <StandardGen name='AtlarusStandard' block='906:14' inherits='PresetStandardGen'> 
                    <Description> Equivalent to vanilla minecraft Cluster distribution. </Description>
                    <DrawWireframe>:=drawWireframes</DrawWireframe>
                    <WireframeColor>0x60101010</WireframeColor>

                    <Setting name='Size' avg=':= 0.375 * atlarusSize * _default_'/> 
                    <Setting name='Frequency' avg=':= 0.05 * atlarusFreq * if(age,age.atlarusClusters,1) * _default_'/>
                    <Setting name='Height' avg=':= 10/128 * dimension.groundLevel' range=':= 10/128 * dimension.groundLevel'/>

  		  <!--1 = 100%  (Normal loads full amount).  0.5 = 50%  (Loads Half as much).  0 = 0%  (None loads in this Biome). -->
                    <BiomeType name='.*' weight='0.5'/>
                    <Biome name='Extreme.*' weight='0.5'/>
                    <Biome name='Hills.*' weight='0.5'/>
                    <Biome name='Cold.*' weight='0.5'/>
                    <Biome name='Ice.*' weight='0.5'/>
                    <Biome name='Frozen.*' weight='0.5'/>
                    <Biome name='Hell.*' weight='-1'/>

                </StandardGen>


		<!-- More Distribution Types can go here -->


            </IfCondition>   
            
        </ConfigSection>
        <!-- ********** / Atlarus ********** -->




        <!-- Additional Ores can go here... -->

        <!--*******************   (Ore)   ***********************-->


        <!-- ********** / (Ore)  ********** -->




    </IfCondition>
    
</ConfigSection>
